pytest_excel/__init__.py
pytest_excel/pytest_excel.py
pytest_excel-1.8.1.dist-info/METADATA
pytest_excel-1.8.1.dist-info/WHEEL
pytest_excel-1.8.1.dist-info/entry_points.txt
pytest_excel-1.8.1.dist-info/RECORD
