Metadata-Version: 2.4
Name: pytest-excel
Version: 1.8.0
Summary: pytest plugin for generating excel reports
Home-page: https://github.com/ssrikanta/pytest-excel
Author: santosh
Author-email: santosh <santosh.srikanta@gmail.com>
License-Expression: MIT
Project-URL: Homepage, https://github.com/ssrikanta/pytest-excel
Project-URL: Source, https://github.com/ssrikanta/pytest-excel
Project-URL: Tracker, https://github.com/ssrikanta/pytest-excel/issues
Keywords: excel,pytest,report
Classifier: Development Status :: 5 - Production/Stable
Classifier: Framework :: Pytest
Classifier: Intended Audience :: Developers
Classifier: Natural Language :: English
Classifier: Operating System :: MacOS :: MacOS X
Classifier: Operating System :: Microsoft :: Windows
Classifier: Operating System :: POSIX
Classifier: Programming Language :: Python :: 3 :: Only
Classifier: Programming Language :: Python :: 3.11
Classifier: Programming Language :: Python :: 3.12
Classifier: Programming Language :: Python :: 3.13
Classifier: Programming Language :: Python :: Implementation :: CPython
Classifier: Programming Language :: Python :: Implementation :: PyPy
Classifier: Topic :: Software Development :: Quality Assurance
Classifier: Topic :: Software Development :: Testing
Classifier: Topic :: Utilities
Requires-Python: >=3.11
License-File: LICENSE
Requires-Dist: pytest
Requires-Dist: pandas
Requires-Dist: openpyxl
Dynamic: author
Dynamic: home-page
Dynamic: license-file
Dynamic: requires-python
